nblm-0.2.2.dist-info/METADATA
nblm-0.2.2.dist-info/WHEEL
nblm/__init__.py
nblm/__init__.pyi
nblm/_auth.pyi
nblm/_client.pyi
nblm/_models.pyi
nblm/nblm.pypy310-pp73-aarch64-linux-gnu.so
nblm/py.typed
nblm-0.2.2.dist-info/RECORD
