Metadata-Version: 2.4
Name: nblm
Version: 0.2.2
Classifier: Development Status :: 3 - Alpha
Classifier: Intended Audience :: Developers
Classifier: License :: OSI Approved :: MIT License
Classifier: Programming Language :: Python :: 3.12
Classifier: Programming Language :: Python :: 3.13
Classifier: Programming Language :: Python :: 3.14
Classifier: Programming Language :: Rust
Classifier: Topic :: Software Development :: Libraries :: Python Modules
Requires-Dist: pytest>=7.0.0 ; extra == 'dev'
Requires-Dist: mypy>=1.0.0 ; extra == 'dev'
Requires-Dist: ruff>=0.1.0 ; extra == 'dev'
Requires-Dist: maturin>=1.0,<2.0 ; extra == 'dev'
Provides-Extra: dev
Summary: Python bindings for NotebookLM Enterprise API client
Keywords: notebooklm,api,google-cloud,gemini
Home-Page: https://github.com/K-dash/nblm-rs
Author: K-dash
License: MIT
Requires-Python: >=3.14
Project-URL: Homepage, https://github.com/K-dash/nblm-rs
Project-URL: Repository, https://github.com/K-dash/nblm-rs
Project-URL: Bug Tracker, https://github.com/K-dash/nblm-rs/issues
